mandoline/TextThermometer.py
mandoline/__init__.py
mandoline/facet3d.py
mandoline/float_fmt.py
mandoline/geometry2d.py
mandoline/line_segment3d.py
mandoline/point3d.py
mandoline/slicer.py
mandoline/stl_data.py
mandoline/vector.py
mandoline_dhee-0.1.dist-info/LICENSE
mandoline_dhee-0.1.dist-info/METADATA
mandoline_dhee-0.1.dist-info/WHEEL
mandoline_dhee-0.1.dist-info/entry_points.txt
mandoline_dhee-0.1.dist-info/top_level.txt
mandoline_dhee-0.1.dist-info/RECORD
